inels_mqtt_wrapper/AbstractDeviceInterface.py
inels_mqtt_wrapper/AbstractDeviceSupportsSet.py
inels_mqtt_wrapper/AbstractDeviceSupportsStatus.py
inels_mqtt_wrapper/__init__.py
inels_mqtt_wrapper/_device_interfaces/DeviceInterface02.py
inels_mqtt_wrapper/_device_interfaces/DeviceInterface03.py
inels_mqtt_wrapper/_device_interfaces/DeviceInterface05.py
inels_mqtt_wrapper/_device_interfaces/DeviceInterface09.py
inels_mqtt_wrapper/_device_interfaces/DeviceInterface10.py
inels_mqtt_wrapper/_device_interfaces/DeviceInterface12.py
inels_mqtt_wrapper/_device_interfaces/DeviceInterface19.py
inels_mqtt_wrapper/_device_interfaces/__init__.py
inels_mqtt_wrapper/_logging.py
inels_mqtt_wrapper/_tasks.py
inels_mqtt_wrapper/concrete_devices.py
inels_mqtt_wrapper/exceptions.py
inels_mqtt_wrapper/utils.py
inels_mqtt_wrapper-0.4.2.dist-info/LICENSE
inels_mqtt_wrapper-0.4.2.dist-info/WHEEL
inels_mqtt_wrapper-0.4.2.dist-info/METADATA
inels_mqtt_wrapper-0.4.2.dist-info/RECORD
