Metadata-Version: 2.1
Name: inels-mqtt-wrapper
Version: 0.4.2
Summary: A Python library to work with Inels devices over MQTT (using Asyncio)
Home-page: https://github.com/Multi-Agent-io/inels-mqtt-wrapper
License: Apache 2.0
Author: arseniiarsenii
Author-email: arseniivelichko2@gmail.com
Requires-Python: >=3.8,<4.0
Classifier: License :: Other/Proprietary License
Classifier: Programming Language :: Python :: 3
Classifier: Programming Language :: Python :: 3.8
Classifier: Programming Language :: Python :: 3.9
Classifier: Programming Language :: Python :: 3.10
Classifier: Programming Language :: Python :: 3.11
Requires-Dist: asyncio-mqtt (>=0.13.0,<0.14.0)
